{"id":"section_45","phaseId":"phase3","order":45,"titleDe":"FSP-Simulation II","title":{"en":"FSP Simulation II","bn":"FSP Simulation II","hi":"FSP Simulation II","ur":"FSP Simulation II","tr":"FSP Simulation II"},"level":"C1","estimatedMinutes":45,"vocabulary":[{"id":"v45_01","germanTerm":"Fachwort","article":"das","plural":"Fachwörter","translation":{"en":"Specialist Term","bn":"বিশেষজ্ঞ শব্দ","hi":"विशेषज्ञ शब्द","ur":"ماہر اصطلاح","tr":"Uzman terimi"}}],"dialogues":[{"id":"d45_01","title":{"en":"FSP Simulation II Scenario"},"lines":[{"speaker":"Facharzt","germanText":"Clinical dialogue for FSP Simulation II.","translation":{"en":"Clinical dialogue for FSP Simulation II."}}]}],"exercises":[{"id":"e45_01","type":"multipleChoice","question":{"en":"Question about FSP Simulation II?"},"options":["A","B","C"],"correctAnswer":"A","points":15}],"media":{"introVideoUrl":"video/sections/section_45/intro.mp4","dialogueVideoUrl":"video/sections/section_45/dialogue.mp4"}}
